k8sconf/__init__.py
k8sconf-0.0.1.dist-info/LICENSE
k8sconf-0.0.1.dist-info/METADATA
k8sconf-0.0.1.dist-info/WHEEL
k8sconf-0.0.1.dist-info/top_level.txt
k8sconf-0.0.1.dist-info/RECORD
